[
    {
        "Id": "",
        "Created": "",
        "Path": "",
        "Args": [
            "",
            ""
        ],
        "State": {
            "Status": "",
            "Running": false,
            "Paused": false,
            "Restarting": false,
            "OOMKilled": false,
            "Dead": false,
            "Pid": 0000,
            "ExitCode": 0,
            "Error": "",
            "StartedAt": "",
            "FinishedAt": ""
        },
        "Image": "",
        "ResolvConfPath": "",
        "HostnamePath": "",
        "HostsPath": "",
        "LogPath": "",
        "Name": "",
        "RestartCount": 0,
        "Driver": "",
        "Platform": "",
        "MountLabel": "",
        "ProcessLabel": "",
        "AppArmorProfile": "",
        "ExecIDs": null,
        "HostConfig": {
            "Binds": [],
            "ContainerIDFile": "",
            "LogConfig": {
                "Type": "",
                "Config": {}
            },
            "NetworkMode": "",
            "PortBindings": {
                "9030/tcp": [
                    {
                        "HostIp": "",
                        "HostPort": ""
                    }
                ]
            },
            "RestartPolicy": {
                "Name": "",
                "MaximumRetryCount": 0
            },
            "AutoRemove": false,
            "VolumeDriver": "",
            "VolumesFrom": [],
            "CapAdd": null,
            "CapDrop": null,
            "Capabilities": null,
            "Dns": null,
            "DnsOptions": null,
            "DnsSearch": null,
            "ExtraHosts": null,
            "GroupAdd": null,
            "IpcMode": "",
            "Cgroup": "",
            "Links": null,
            "OomScoreAdj": 0,
            "PidMode": "",
            "Privileged": false,
            "PublishAllPorts": false,
            "ReadonlyRootfs": false,
            "SecurityOpt": null,
            "UTSMode": "",
            "UsernsMode": "",
            "ShmSize": 00000000,
            "Runtime": "",
            "ConsoleSize": [
                0,
                0
            ],
            "Isolation": "",
            "CpuShares": 0,
            "Memory": 0,
            "NanoCpus": 0,
            "CgroupParent": "",
            "BlkioWeight": 0,
            "BlkioWeightDevice": null,
            "BlkioDeviceReadBps": null,
            "BlkioDeviceWriteBps": null,
            "BlkioDeviceReadIOps": null,
            "BlkioDeviceWriteIOps": null,
            "CpuPeriod": 0,
            "CpuQuota": 0,
            "CpuRealtimePeriod": 0,
            "CpuRealtimeRuntime": 0,
            "CpusetCpus": "",
            "CpusetMems": "",
            "Devices": null,
            "DeviceCgroupRules": null,
            "DeviceRequests": null,
            "KernelMemory": 0,
            "KernelMemoryTCP": 0,
            "MemoryReservation": 0,
            "MemorySwap": 0,
            "MemorySwappiness": null,
            "OomKillDisable": false,
            "PidsLimit": null,
            "Ulimits": null,
            "CpuCount": 0,
            "CpuPercent": 0,
            "IOMaximumIOps": 0,
            "IOMaximumBandwidth": 0,
            "MaskedPaths": [
                ""
            ],
            "ReadonlyPaths": [
                ""
            ]
        },
        "GraphDriver": {
            "Data": {
                "LowerDir": "",
                "MergedDir": "",
                "UpperDir": "",
                "WorkDir": ""
            },
            "Name": ""
        },
        "Mounts": [],
        "Config": {
            "Hostname": "",
            "Domainname": "",
            "User": "",
            "AttachStdin": false,
            "AttachStdout": false,
            "AttachStderr": false,
            "ExposedPorts": {
                "9030/tcp": {}
            },
            "Tty": false,
            "OpenStdin": false,
            "StdinOnce": false,
            "Env": [
                "APP_URL=",
                "APP_PORT=",
                "APP_RUNNING_MODE=",
                "PATH=",
                "NODE_VERSION=",
                "YARN_VERSION="
            ],
            "Cmd": [
                ""
            ],
            "Image": "",
            "Volumes": null,
            "WorkingDir": "",
            "Entrypoint": [
                ""
            ],
            "OnBuild": null,
            "Labels": {
                "com.docker.compose.config-hash": "",
                "com.docker.compose.container-number": "",
                "com.docker.compose.oneoff": "",
                "com.docker.compose.project": "",
                "com.docker.compose.service": "",
                "com.docker.compose.version": ""
            }
        },
        "NetworkSettings": {
            "Bridge": "",
            "SandboxID": "",
            "HairpinMode": false,
            "LinkLocalIPv6Address": "",
            "LinkLocalIPv6PrefixLen": 0,
            "Ports": {
                "9030/tcp": [
                    {
                        "HostIp": "",
                        "HostPort": ""
                    }
                ]
            },
            "SandboxKey": "",
            "SecondaryIPAddresses": null,
            "SecondaryIPv6Addresses": null,
            "EndpointID": "",
            "Gateway": "",
            "GlobalIPv6Address": "",
            "GlobalIPv6PrefixLen": 0,
            "IPAddress": "",
            "IPPrefixLen": 0,
            "IPv6Gateway": "",
            "MacAddress": "",
            "Networks": {
                "docker-nodejs-simple-api_default": {
                    "IPAMConfig": null,
                    "Links": null,
                    "Aliases": [
                        "",
                        ""
                    ],
                    "NetworkID": "",
                    "EndpointID": "",
                    "Gateway": "",
                    "IPAddress": "",
                    "IPPrefixLen": 0,
                    "IPv6Gateway": "",
                    "GlobalIPv6Address": "",
                    "GlobalIPv6PrefixLen": 0,
                    "MacAddress": "",
                    "DriverOpts": null
                }
            }
        }
    }
]